{
  "FixOOBEInput": {
    "service": [
      {
        "Name": "TextInputManagementService",
        "StartupType": "AutomaticDelayedStart"
      }
    ]
  },
  "ImFeelingSafe": {
    "service": [
      {
        "Name": "SecurityHealthService",
        "StartupType": "Disabled"
      },
      {
        "Name": "webthreatdefsvc",
        "StartupType": "Disabled"
      },
      {
        "Name": "webthreatdefusersvc",
        "StartupType": "Disabled"
      },
      {
        "Name": "WpnUserService",
        "StartupType": "Disabled"
      }
    ]
  },
  "DumberNotification": {
    "registry": [
      {
        "Path": "HKCU:\\Software\\Microsoft\\Windows\\CurrentVersion\\Notifications\\Settings\\Windows.ActionCenter.SmartOptOut",
        "Name": "Enabled",
        "Value": "0",
        "Type": "DWord"
      },
      {
        "Path": "HKCU:\\Software\\Microsoft\\Windows\\CurrentVersion\\Explorer\\Advanced",
        "Name": "StartShownOnUpgrade",
        "Value": "1",
        "Type": "DWord"
      }
    ]
  },
  "OfflineOOBE": {
    "registry": [
      {
        "Path": "HKLM:\\SOFTWARE\\Microsoft\\Windows\\CurrentVersion\\Setup\\OOBE\\NDUP",
        "Name": "EnableExpeditedUpdate",
        "Value": "0",
        "Type": "DWord"
      },
      {
        "Path": "HKLM:\\SOFTWARE\\Microsoft\\Windows\\CurrentVersion\\Setup\\OOBE",
        "Name": "SetupDisplayedEula",
        "Value": "1",
        "Type": "DWord"
      },
      {
        "Path": "HKLM:\\SOFTWARE\\Microsoft\\Windows\\CurrentVersion\\Setup\\OOBE",
        "Name": "SetupDisplayedLanguageSelection",
        "Value": "1",
        "Type": "DWord"
      },
      {
        "Path": "HKLM:\\SOFTWARE\\Microsoft\\Windows\\CurrentVersion\\Setup\\OOBE",
        "Name": "SetupDisplayedProductKey",
        "Value": "1",
        "Type": "DWord"
      },
      {
        "Path": "HKCU:\\Software\\Microsoft\\Windows\\CurrentVersion\\CloudExperienceHost\\Intent\\PersonalDataExport",
        "Name": "PDEShown",
        "Value": "2",
        "Type": "DWord"
      }
    ]
  },
  "EndTaskOnTaskbar": {
    "registry": [
      {
        "Path": "HKCU:\\Software\\Microsoft\\Windows\\CurrentVersion\\Explorer\\Advanced\\TaskbarDeveloperSettings",
        "Name": "TaskbarEndTask",
        "Value": "1",
        "Type": "DWord"
      }
    ]
  },
  "GamingOnly": {
    "service": [
      {
        "Name": "ShellHWDetection",
        "StartupType": "Disabled"
      },
      {
        "Name": "lfsvc",
        "StartupType": "Disabled"
      },
      {
        "Name": "iphlpsvc",
        "StartupType": "Disabled"
      },
      {
        "Name": "BthAvctpSvc",
        "StartupType": "Disabled"
      },
      {
        "Name": "Spooler",
        "StartupType": "Manual"
      },
      {
        "Name": "SSDPSRV",
        "StartupType": "Disabled"
      },
      {
        "Name": "SDRSVC",
        "StartupType": "Disabled"
      },
      {
        "Name": "WSearch",
        "StartupType": "Disabled"
      },
      {
        "Name": "WLANSVC",
        "StartupType": "Disabled"
      },
      {
        "Name": "WpnService",
        "StartupType": "Disabled"
      },
      {
        "Name": "pcasvc",
        "StartupType": "Disabled"
      },
      {
        "Name": "camsvc",
        "StartupType": "Manual"
      },
      {
        "Name": "cdpsvc",
        "StartupType": "Manual"
      },
      {
        "Name": "CDPUsersvc",
        "StartupType": "Manual"
      },
      {
        "Name": "InventorySvc",
        "StartupType": "Disabled"
      },
      {
        "Name": "RmSvc",
        "StartupType": "Disabled"
      },
      {
        "Name": "DusmSvc",
        "StartupType": "Disabled"
      },
      {
        "Name": "OneSyncSvc",
        "StartupType": "Disabled"
      },
      {
        "Name": "BDESVC",
        "StartupType": "Disabled"
      },
      {
        "Name": "BITS",
        "StartupType": "Manual"
      },
      {
        "Name": "DoSVC",
        "StartupType": "Manual"
      },
      {
        "Name": "DsmSvc",
        "StartupType": "Disabled"
      },
      {
        "Name": "cbdhsvc",
        "StartupType": "Disabled"
      },
      {
        "Name": "CloudBackupRestoreSvc",
        "StartupType": "Disabled"
      },
      {
        "Name": "bthserv",
        "StartupType": "Disabled"
      },
      {
        "Name": "BTAGService",
        "StartupType": "Disabled"
      },
      {
        "Name": "WinHttpAutoProxySvc",
        "StartupType": "Disabled"
      },
      {
        "Name": "wscsvc",
        "StartupType": "Disabled"
      },
      {
        "Name": "PushToInstall",
        "StartupType": "Disabled"
      }
    ]
  },
  "AllowExecutionPowershell": {
    "registry": [
      {
        "Path": "HKLM:\\Software\\Microsoft\\PowerShell\\1\\ShellIds\\Microsoft.PowerShell",
        "Name": "ExecutionPolicy",
        "Value": "Unrestricted",
        "Type": "String"
      }
    ]
  },
  "DetailedBsod": {
    "registry": [
      {
        "Path": "HKLM:\\System\\ControlSet001\\Control\\CrashControl",
        "Name": "DisplayParameters",
        "Value": "1",
        "Type": "DWord"
      }
    ]
  },
  "DisableHibernation": {
    "registry": [
      {
        "Path": "HKLM:\\System\\ControlSet001\\Control\\Power",
        "Name": "HibernateEnabled",
        "Value": "0",
        "Type": "DWord"
      }
    ]
  },
  "DisableSwapFile": {
    "registry": [
      {
        "Path": "HKLM:\\System\\ControlSet001\\Control\\Session Manager\\Memory Management",
        "Name": "SwapfileControl",
        "Value": "0",
        "Type": "DWord"
      }
    ]
  },
  "DisableWindowArrangement": {
    "registry": [
      {
        "Path": "HKCU:\\Control Panel\\Desktop",
        "Name": "WindowArrangementActive",
        "Value": "0",
        "Type": "DWord"
      },
      {
        "Path": "HKCU:\\SOFTWARE\\Microsoft\\Windows\\CurrentVersion\\Explorer\\Advanced",
        "Name": "MultiTaskingAltTabFilter",
        "Value": "3",
        "Type": "DWord"
      }
    ]
  },
  "DisableStorageSense": {
    "registry": [
      {
        "Path": "HKCU:\\SOFTWARE\\Microsoft\\Windows\\CurrentVersion\\StorageSense\\Parameters\\StoragePolicy",
        "Name": "01",
        "Value": "0",
        "Type": "DWord"
      }
    ]
  },
  "DisableVulnerableDriverBlocklist": {
    "registry": [
      {
        "Path": "HKLM:\\System\\ControlSet001\\Control\\CI\\Config",
        "Name": "VulnerableDriverBlocklistEnable",
        "Value": "0",
        "Type": "DWord"
      }
    ]
  },
  "RealTimeIsUniversal": {
    "registry": [
      {
        "Path": "HKLM:\\System\\ControlSet001\\Control\\TimeZoneInformation",
        "Name": "RealTimeIsUniversal",
        "Value": "1",
        "Type": "DWord"
      }
    ]
  },
  "SkipFirstLogonAnimation": {
    "registry": [
      {
        "Path": "HKLM:\\Software\\Microsoft\\Windows\\CurrentVersion\\Policies\\System",
        "Name": "EnableFirstLogonAnimation",
        "Value": "0",
        "Type": "DWord"
      },
      {
        "Path": "HKLM:\\Software\\Microsoft\\Windows\\CurrentVersion\\Policies\\System",
        "Name": "DelayedDesktopSwitchTimeout",
        "Value": "0",
        "Type": "DWord"
      }
    ]
  },
  "VerboseStatusMessages": {
    "registry": [
      {
        "Path": "HKLM:\\SOFTWARE\\Microsoft\\Windows\\CurrentVersion\\Policies\\System",
        "Name": "VerboseStatus",
        "Value": "1",
        "Type": "DWord"
      }
    ]
  },
  "DisableClipboardHistory": {
    "registry": [
      {
        "Path": "HKLM:\\SOFTWARE\\Microsoft\\Clipboard",
        "Name": "IsCloudAndHistoryFeatureAvailable",
        "Value": "0",
        "Type": "DWord"
      }
    ]
  },
  "NoDisplayIdle": {
    "registry": [
      {
        "Path": "HKLM:\\Software\\Policies\\Microsoft\\Power\\PowerSettings\\3C0BC021-C8A8-4E07-A973-6B14CBCB2B7E",
        "Name": "ACSettingIndex",
        "Value": "0",
        "Type": "DWord"
      }
    ]
  },
  "TweakChsIME": {
    "registry": [
      {
        "Path": "HKCU:\\SOFTWARE\\Microsoft\\InputMethod\\Settings\\CHS",
        "Name": "EnableChineseEnglishPunctuationSwitch",
        "Value": "0",
        "Type": "DWord"
      },
      {
        "Path": "HKCU:\\SOFTWARE\\Microsoft\\InputMethod\\Settings\\CHS",
        "Name": "EnableSimplifiedTraditionalOutputSwitch",
        "Value": "0",
        "Type": "DWord"
      },
      {
        "Path": "HKCU:\\SOFTWARE\\Microsoft\\InputMethod\\Settings\\CHS",
        "Name": "Enable Cloud Candidate",
        "Value": "0",
        "Type": "DWord"
      }
    ]
  },
  "RdpSoftwareRender": {
    "registry": [
      {
        "Path": "HKLM:\\SOFTWARE\\Policies\\Microsoft\\Windows NT\\Terminal Services",
        "Name": "bEnumerateHWBeforeSW",
        "Value": "1",
        "Type": "DWord"
      }
    ]
  },
  "EnableSudo": {
    "registry": [
      {
        "Path": "HKLM:\\SOFTWARE\\Microsoft\\Windows\\CurrentVersion\\Sudo",
        "Name": "Enabled",
        "Value": "3",
        "Type": "DWord"
      }
    ]
  },
  "MorePins": {
    "registry": [
      {
        "Path": "HKCU:\\Software\\Microsoft\\Windows\\CurrentVersion\\Explorer\\Advanced",
        "Name": "Start_Layout",
        "Value": "1",
        "Type": "DWord"
      }
    ]
  },
  "PinnedFolders": {
    "registry": [
      {
        "Path": "HKLM:\\Software\\Microsoft\\PolicyManager\\current\\device\\Start",
        "Name": "AllowPinnedFolderSettings",
        "Value": "1",
        "Type": "DWord"
      },
      {
        "Path": "HKLM:\\Software\\Microsoft\\PolicyManager\\current\\device\\Start",
        "Name": "AllowPinnedFolderSettings_ProviderSet",
        "Value": "1",
        "Type": "DWord"
      },
      {
        "Path": "HKLM:\\Software\\Microsoft\\PolicyManager\\current\\device\\Start",
        "Name": "AllowPinnedFolderDownloads",
        "Value": "1",
        "Type": "DWord"
      },
      {
        "Path": "HKLM:\\Software\\Microsoft\\PolicyManager\\current\\device\\Start",
        "Name": "AllowPinnedFolderDownloads_ProviderSet",
        "Value": "1",
        "Type": "DWord"
      },
      {
        "Path": "HKLM:\\Software\\Microsoft\\PolicyManager\\current\\device\\Start",
        "Name": "AllowPinnedFolderPersonalFolder",
        "Value": "1",
        "Type": "DWord"
      },
      {
        "Path": "HKLM:\\Software\\Microsoft\\PolicyManager\\current\\device\\Start",
        "Name": "AllowPinnedFolderPersonalFolder_ProviderSet",
        "Value": "1",
        "Type": "DWord"
      },
      {
        "Path": "HKLM:\\Software\\Microsoft\\PolicyManager\\current\\device\\Start",
        "Name": "AllowPinnedFolderDocuments",
        "Value": "1",
        "Type": "DWord"
      },
      {
        "Path": "HKLM:\\Software\\Microsoft\\PolicyManager\\current\\device\\Start",
        "Name": "AllowPinnedFolderDocuments_ProviderSet",
        "Value": "1",
        "Type": "DWord"
      }
    ]
  },
  "NoStickyToggleMouseFilterKeys": {
    "registry": [
      {
        "Path": "HKCU:\\Control Panel\\Accessibility\\StickyKeys",
        "Name": "Flags",
        "Value": "506",
        "Type": "String"
      },
      {
        "Path": "HKCU:\\Control Panel\\Accessibility\\ToggleKeys",
        "Name": "Flags",
        "Value": "62",
        "Type": "String"
      },
      {
        "Path": "HKCU:\\Control Panel\\Accessibility\\MouseKeys",
        "Name": "Flags",
        "Value": "62",
        "Type": "String"
      },
      {
        "Path": "HKCU:\\Control Panel\\Accessibility\\Keyboard Response",
        "Name": "Flags",
        "Value": "122",
        "Type": "String"
      }
    ]
  }
}